[
    {
        "product_id": "LAP001",
        "product_title": "Dell XPS 13 UltraBook",
        "product_image": "https://i.ibb.co.com/xmVWW2F/download-1.jpg",
        "category": "Laptops",
        "price": 1200,
        "description": "High-performance ultrabook with long battery life.",
        "Specification": ["16GB RAM", "512GB SSD", "Intel i7"],
        "availability": true,
        "rating": 4.7,
        "buttonAction": "/Laptops/LAP001"
    },
    {
        "product_id": "LAP002",
        "product_title": "Asus ROG Strix Gaming Beast X",
        "product_image": "https://i.ibb.co.com/bR1qjsc/download-2.jpg",
        "category": "Laptops",
        "price": 1800,
        "description": "Ultimate gaming laptop with top-notch graphics.",
        "Specification": ["32GB RAM", "1TB SSD", "NVIDIA RTX 3070"],
        "availability": true,
        "rating": 4.9,
        "buttonAction": "/Laptops/LAP002"
    },
    {
        "product_id": "LAP003",
        "product_title": "HP Pavilion Budget Friendly",
        "product_image": "https://i.ibb.co.com/Bg4zfMM/download-3.jpg",
        "category": "Laptops",
        "price": 600,
        "description": "Affordable laptop for everyday tasks.",
        "Specification": ["8GB RAM", "256GB SSD", "Intel i3"],
        "availability": true,
        "rating": 4.2,
        "buttonAction": "/Laptops/LAP003"
    },
    {
        "product_id": "LAP004",
        "product_title": "Apple MacBook Pro Creative Studio",
        "product_image": "https://i.ibb.co.com/VDTWr5d/images-3.jpg",
        "category": "Laptops",
        "price": 2000,
        "description": "Perfect laptop for creators and designers.",
        "Specification": ["32GB RAM", "1TB SSD", "Apple M1 Max", "4K Display"],
        "availability": false,
        "rating": 4.8,
        "buttonAction": "/Laptops/LAP004"
    },
    {
        "product_id": "LAP005",
        "product_title": "Lenovo ThinkPad Student Companion",
        "product_image": "https://i.ibb.co.com/py0fgCy/download-4.jpg",
        "category": "Laptops",
        "price": 700,
        "description": "Lightweight laptop ideal for students.",
        "Specification": ["8GB RAM", "512GB SSD", "Intel i5"],
        "availability": true,
        "rating": 4.3,
        "buttonAction": "/Laptops/LAP005"
    },
    {
        "product_id": "LAP006",
        "product_title": "HP EliteBook Business Elite",
        "product_image": "https://i.ibb.co.com/2yyGh8N/download-5.jpg",
        "category": "Laptops",
        "price": 1500,
        "description": "Powerful laptop with enhanced security for business.",
        "Specification": ["16GB RAM", "1TB SSD", "Intel i7", "Fingerprint Reader"],
        "availability": true,
        "rating": 4.6,
        "buttonAction": "/Laptops/LAP006"
    },
    {
        "product_id": "PHN001",
        "product_title": "Apple iPhone 15 Pro Max",
        "product_image": "https://i.ibb.co.com/d0g1nkk/download-6.jpg",
        "category": "Smartphones",
        "price": 1299,
        "description": "Experience the ultimate smartphone with the iPhone 15 Pro Max.",
        "Specification": ["6.7-inch Super Retina XDR display", "A17 Bionic chip", "Triple-camera system (48MP Main, 12MP Telephoto, 12MP Ultrawide)", "LiDAR Scanner", "Up to 2TB storage"],
        "availability": true,
        "rating": 4.8,
        "buttonAction": "/Smartphones/PHN001"
    },
    {
        "product_id": "PHN002",
        "product_title": "Samsung Galaxy S23 Ultra",
        "product_image": "https://i.ibb.co.com/H2bnwgt/download-7.jpg",
        "category": "Smartphones",
        "price": 1200,
        "description": "Capture the world with the incredible Galaxy S23 Ultra camera.",
        "Specification": ["6.8-inch QHD+ Dynamic AMOLED", "Snapdragon 8 Gen 2", "Quad-camera system (200MP, 12MP, 10MP, 10MP)", "5000mAh battery"],
        "availability": true,
        "rating": 4.7,
        "buttonAction": "/Smartphones/PHN002"
    },
    {
        "product_id": "PHN003",
        "product_title": "Google Pixel 8 Pro",
        "product_image": "https://i.ibb.co.com/jWzL4jB/download-8.jpg",
        "category": "Smartphones",
        "price": 1000,
        "description": "The smart choice with Google’s best-in-class AI features.",
        "Specification": ["6.7-inch LTPO OLED", "Google Tensor G3", "Triple-camera system (50MP, 48MP, 12MP)", "24-hour battery life"],
        "availability": false,
        "rating": 4.6,
        "buttonAction": "/Smartphones/PHN003"
    },
    {
        "product_id": "WCH001",
        "product_title": "Apple Watch Series 9",
        "product_image": "https://i.ibb.co.com/m4RQdqq/download-9.jpg",
        "category": "Watches",
        "price": 400,
        "description": "Advanced health and fitness tracking with the new Series 9.",
        "Specification": ["Always-On Retina display", "S9 SiP", "Blood Oxygen and ECG apps"],
        "availability": true,
        "rating": 4.7,
        "buttonAction": "/Watches/WCH001"
    },
    {
        "product_id": "WCH002",
        "product_title": "Samsung Galaxy Watch 6",
        "product_image": "https://i.ibb.co.com/p0gj7SJ/download-10.jpg",
        "category": "Watches",
        "price": 350,
        "description": "Your ultimate companion for a healthier lifestyle.",
        "Specification": ["1.5-inch Super AMOLED", "Exynos W930", "Heart Rate Monitor", "Sleep Tracking"],
        "availability": true,
        "rating": 4.5,
        "buttonAction": "/Watches/WCH002"
    },
    {
        "product_id": "WCH003",
        "product_title": "Garmin Forerunner 965",
        "product_image": "https://i.ibb.co.com/1bTFWDV/download-11.jpg",
        "category": "Watches",
        "price": 600,
        "description": "Perfect for athletes, with advanced fitness and health tracking.",
        "Specification": ["1.4-inch AMOLED", "Garmin Connect", "VO2 max tracking", "Pulse Ox sensor"],
        "availability": false,
        "rating": 4.8,
        "buttonAction": "/Watches/WCH003"
    },
    {
        "product_id": "KBD005",
        "product_title": "HyperX Alloy FPS Pro",
        "product_image": "https://i.ibb.co.com/H7W7qqH/images-4.jpg",
        "category": "Keyboards",
        "price": 110,
        "description": "Compact, tenkeyless mechanical keyboard built for FPS gamers.",
        "Specification": ["Cherry MX mechanical key switches", "Red LED backlighting", "Durable steel frame", "Portable and lightweight"],
        "availability": true,
        "rating": 4.6,
        "buttonAction": "/Keyboards/KBD005"
    },
     {
        "product_id": "KBD004",
        "product_title": "SteelSeries Apex Pro",
        "product_image": "https://i.ibb.co.com/KXKvq6C/download-12.jpg",
        "category": "Keyboards",
        "price": 250,
        "description": "Premium mechanical keyboard with adjustable actuation switches.",
        "Specification": ["OmniPoint adjustable switches", "RGB illumination", "Aircraft-grade aluminum frame", "USB passthrough"],
        "availability": true,
        "rating": 4.9,
        "buttonAction": "/Keyboards/KBD004"
    },
    {
        "product_id": "KBD003",
        "product_title": "Razer BlackWidow V3",
        "product_image": "https://i.ibb.co.com/WFtbPH5/download-13.jpg",
        "category": "Keyboards",
        "price": 120,
        "description": "Mechanical gaming keyboard with Razer Green switches and RGB Chroma backlighting.",
        "Specification": ["Razer Green switches", "RGB Chroma backlighting", "Media controls", "Ergonomic wrist rest"],
        "availability": true,
        "rating": 4.8,
        "buttonAction": "/Keyboards/KBD003"
    },
    {
        "product_id": "KBD002",
        "product_title": "Logitech G Pro X",
        "product_image": "https://i.ibb.co.com/yWTcpxC/images-5.jpg",
        "category": "Keyboards",
        "price": 130,
        "description": "Customizable mechanical keyboard designed for esports professionals.",
        "Specification": ["Hot-swappable switches", "RGB lighting", "Tenkeyless design", "Detachable cable"],
        "availability": true,
        "rating": 4.7,
        "buttonAction": "/Keyboards/KBD002"
    }
]
